tushare_interface/__init__.py
tushare_interface/tushare_interface.py
tushare_interface-0.2.0.dist-info/LICENSE
tushare_interface-0.2.0.dist-info/METADATA
tushare_interface-0.2.0.dist-info/WHEEL
tushare_interface-0.2.0.dist-info/top_level.txt
tushare_interface-0.2.0.dist-info/RECORD
