Metadata-Version: 2.1
Name: tushare_interface
Version: 0.2.0
Summary: An interface encapsulated based on Tushare, which implements rate limiting and retry mechanisms.
Author-email: polaritec <yuan.xin@polaritec.com>
Project-URL: Homepage, https://github.com/polaritec/tushare-interface
Keywords: tushare,stock
Classifier: Development Status :: 4 - Beta
Classifier: License :: OSI Approved :: Apache Software License
Classifier: Programming Language :: Python
Classifier: Programming Language :: Python :: 3
Classifier: Programming Language :: Python :: 3.10
Requires-Python: >=3.10
License-File: LICENSE
Requires-Dist: tushare >=1.4.5
Requires-Dist: pandas >=2.2.1
